oneNeuron/__init__.py
oneNeuron/perceptron.py
neuronZeal_pypi_ANKITZEAL-0.0.2.dist-info/LICENSE
neuronZeal_pypi_ANKITZEAL-0.0.2.dist-info/METADATA
neuronZeal_pypi_ANKITZEAL-0.0.2.dist-info/WHEEL
neuronZeal_pypi_ANKITZEAL-0.0.2.dist-info/top_level.txt
neuronZeal_pypi_ANKITZEAL-0.0.2.dist-info/RECORD
