Metadata-Version: 2.1
Name: neuronZeal-pypi-ANKITZEAL
Version: 0.0.2
Summary: Its a implementation of perceptron
Home-page: https://github.com/ANKITZEAL/neuronZeal_pypi 
Author: USER_NAME
Author-email: ankitzeal@gmail.com
License: UNKNOWN
Project-URL: Bug Tracker, https://github.com/ANKITZEAL/neuronZeal_pypi /issues
Platform: UNKNOWN
Classifier: Programming Language :: Python :: 3
Classifier: License :: OSI Approved :: MIT License
Classifier: Operating System :: OS Independent
Requires-Python: >=3.7
License-File: LICENSE
Requires-Dist: numpy
Requires-Dist: tqdm
